pbr/__init__.py
pbr/build.py
pbr/extra_files.py
pbr/find_package.py
pbr/git.py
pbr/options.py
pbr/packaging.py
pbr/pbr_json.py
pbr/setupcfg.py
pbr/sphinxext.py
pbr/version.py
pbr/_compat/__init__.py
pbr/_compat/command_hooks.py
pbr/_compat/commands.py
pbr/_compat/easy_install.py
pbr/_compat/five.py
pbr/_compat/metadata.py
pbr/_compat/packaging.py
pbr/_compat/versions.py
pbr/cmd/__init__.py
pbr/cmd/main.py
pbr/hooks/__init__.py
pbr/hooks/backwards.py
pbr/hooks/base.py
pbr/hooks/files.py
pbr/hooks/metadata.py
pbr/tests/__init__.py
pbr/tests/base.py
pbr/tests/fixtures.py
pbr/tests/test_files.py
pbr/tests/test_git.py
pbr/tests/test_packaging.py
pbr/tests/test_pbr_json.py
pbr/tests/test_setupcfg.py
pbr/tests/test_version.py
pbr/tests/util.py
pbr/tests/_compat/__init__.py
pbr/tests/_compat/test_easy_install.py
pbr/tests/functional/__init__.py
pbr/tests/functional/base.py
pbr/tests/functional/test_c_extension.py
pbr/tests/functional/test_changelog_author.py
pbr/tests/functional/test_commands.py
pbr/tests/functional/test_console_scripts.py
pbr/tests/functional/test_extra_files.py
pbr/tests/functional/test_hooks.py
pbr/tests/functional/test_integration.py
pbr/tests/functional/test_pbr_json.py
pbr/tests/functional/test_pep517.py
pbr/tests/functional/test_requirements.py
pbr/tests/functional/test_wsgi_scripts.py
pbr/tests/testpackage/CHANGES.txt
pbr/tests/testpackage/LICENSE.txt
pbr/tests/testpackage/MANIFEST.in
pbr/tests/testpackage/README.txt
pbr/tests/testpackage/extra-file.txt
pbr/tests/testpackage/git-extra-file.txt
pbr/tests/testpackage/setup.cfg
pbr/tests/testpackage/setup.py
pbr/tests/testpackage/test-requirements.txt
pbr/tests/testpackage/data_files/a.txt
pbr/tests/testpackage/data_files/b.txt
pbr/tests/testpackage/data_files/c.rst
pbr/tests/testpackage/doc/source/conf.py
pbr/tests/testpackage/doc/source/index.rst
pbr/tests/testpackage/doc/source/installation.rst
pbr/tests/testpackage/doc/source/usage.rst
pbr/tests/testpackage/pbr_testpackage/__init__.py
pbr-7.0.3.dist-info/AUTHORS
pbr-7.0.3.dist-info/LICENSE
pbr-7.0.3.dist-info/METADATA
pbr-7.0.3.dist-info/WHEEL
pbr-7.0.3.dist-info/entry_points.txt
pbr-7.0.3.dist-info/top_level.txt
pbr-7.0.3.dist-info/RECORD
