Metadata-Version: 2.1
Name: pbr
Version: 7.0.3
Summary: Python Build Reasonableness
Home-page: https://docs.openstack.org/pbr/latest/
Author: OpenStack
Author-email: openstack-discuss@lists.openstack.org
License: Apache-2.0
Project-URL: Bug Tracker, https://bugs.launchpad.net/pbr/
Project-URL: Documentation, https://docs.openstack.org/pbr/
Project-URL: Source Code, https://opendev.org/openstack/pbr
Classifier: Development Status :: 5 - Production/Stable
Classifier: Environment :: Console
Classifier: Environment :: OpenStack
Classifier: Intended Audience :: Developers
Classifier: Intended Audience :: Information Technology
Classifier: Operating System :: OS Independent
Classifier: Programming Language :: Python
Classifier: Programming Language :: Python :: 2
Classifier: Programming Language :: Python :: 2.7
Classifier: Programming Language :: Python :: 3
Classifier: Programming Language :: Python :: 3.5
Classifier: Programming Language :: Python :: 3.6
Classifier: Programming Language :: Python :: 3.7
Classifier: Programming Language :: Python :: 3.8
Classifier: Programming Language :: Python :: 3.9
Classifier: Programming Language :: Python :: 3.10
Classifier: Programming Language :: Python :: 3.11
Requires-Python: >=2.6
License-File: LICENSE
Requires-Dist: setuptools
